qrgb/__init__.py
qrgb/cli.py
qrgb/qrgb.py
qrgb/webapp.py
qrgb-1.0.2.dist-info/METADATA
qrgb-1.0.2.dist-info/WHEEL
qrgb-1.0.2.dist-info/entry_points.txt
qrgb-1.0.2.dist-info/RECORD
