Metadata-Version: 2.4
Name: qrgb
Version: 1.0.2
Summary: Multi-color QR codes that store 3x more data using RGB channels
Project-URL: Homepage, https://github.com/shyftxero/qrgb
Project-URL: Repository, https://github.com/shyftxero/qrgb
Project-URL: Issues, https://github.com/shyftxero/qrgb/issues
Author-email: Eli McRae <shyft@shyft.us>
License: MIT
Keywords: color,encoding,qr,qrcode,rgb
Classifier: Development Status :: 4 - Beta
Classifier: Intended Audience :: Developers
Classifier: License :: OSI Approved :: MIT License
Classifier: Programming Language :: Python :: 3
Classifier: Programming Language :: Python :: 3.8
Classifier: Programming Language :: Python :: 3.9
Classifier: Programming Language :: Python :: 3.10
Classifier: Programming Language :: Python :: 3.11
Classifier: Programming Language :: Python :: 3.12
Classifier: Programming Language :: Python :: 3.13
Classifier: Topic :: Multimedia :: Graphics
Classifier: Topic :: Software Development :: Libraries :: Python Modules
Requires-Python: >=3.8
Requires-Dist: flask
Requires-Dist: gunicorn>=23.0.0
Requires-Dist: numpy
Requires-Dist: pillow
Requires-Dist: pyzbar
Requires-Dist: qrcode
Requires-Dist: rich
Requires-Dist: typer
Requires-Dist: werkzeug
